nb_libs/__init__.py
nb_libs/auto_git.py
nb_libs/code_line_statistics.py
nb_libs/dict2json.py
nb_libs/github_git_clone.py
nb_libs/global_dict.py
nb_libs/http_utils.py
nb_libs/lazy_importer.py
nb_libs/markdown2pdf.py
nb_libs/memory_leak_analysis.py
nb_libs/nb_time.py
nb_libs/path_helper.py
nb_libs/pydantic_helper.py
nb_libs/redis_key.py
nb_libs/restart_programe_by_interval.py
nb_libs/str_utils.py
nb_libs/sys_frame_uitils.py
tests/__init__.py
tests/t_mem_leak.py
tests/t_mem_leak2.py
tests/t_mem_leak3.py
tests/test_restart_programe_by_interval.py
tests/test_sifn.py
tests/testai.py
tests/tests_time.py
nb_libs-2.0.dist-info/METADATA
nb_libs-2.0.dist-info/WHEEL
nb_libs-2.0.dist-info/top_level.txt
nb_libs-2.0.dist-info/RECORD
