Metadata-Version: 2.1
Name: nb-libs
Version: 2.0
Summary: nb_libs 不想分开分发很多个不同功能单独的包,各种小功能杂项放在一起,具体功能看代码.
Home-page: https://github.com/ydf0509/nb_libs
Author: bfzs
Author-email: ydf0509@sohu.com
Maintainer: ydf
Maintainer-email: ydf0509@sohu.com
License: BSD License
Keywords: nb_libs
Platform: all
Classifier: Development Status :: 4 - Beta
Classifier: Operating System :: OS Independent
Classifier: Intended Audience :: Developers
Classifier: License :: OSI Approved :: BSD License
Classifier: Programming Language :: Python
Classifier: Programming Language :: Python :: Implementation
Classifier: Programming Language :: Python :: 3
Classifier: Topic :: Software Development :: Libraries
Requires-Dist: nb-log
Requires-Dist: tzlocal
Requires-Dist: pytz
